geoedfengine/GeoEDFConfig.py
geoedfengine/GeoEDFWorkflow.py
geoedfengine/WorkflowEngine.py
geoedfengine/__init__.py
geoedfengine/helper/GeoEDFConnector.py
geoedfengine/helper/GeoEDFError.py
geoedfengine/helper/GeoEDFProcessor.py
geoedfengine/helper/PegasusBroker.py
geoedfengine/helper/SubmitBroker.py
geoedfengine/helper/WorkflowBuilder.py
geoedfengine/helper/WorkflowDBHelper.py
geoedfengine/helper/WorkflowUtils.py
geoedfengine/helper/__init__.py
geoedfengine-1.83.data/data/config/geoedf.cfg
geoedfengine-1.83.data/scripts/build-conn-plugin-subdax
geoedfengine-1.83.data/scripts/build-final-subdax
geoedfengine-1.83.data/scripts/build-proc-plugin-subdax
geoedfengine-1.83.dist-info/LICENSE
geoedfengine-1.83.dist-info/METADATA
geoedfengine-1.83.dist-info/WHEEL
geoedfengine-1.83.dist-info/top_level.txt
geoedfengine-1.83.dist-info/RECORD
