Metadata-Version: 2.1
Name: geoedfengine
Version: 1.83
Summary: GeoEDF Plug-and-play Workflow Engine
Home-page: http://github.com/geoedf/engine
Author: Rajesh Kalyanam
Author-email: rkalyanapurdue@gmail.com
License: MIT
Platform: UNKNOWN
Requires-Python: ~=3.6
License-File: LICENSE
Requires-Dist: pyyaml (>5.1)
Requires-Dist: regex
Requires-Dist: cryptography
Requires-Dist: sregistry
Requires-Dist: requests-toolbelt
